biocartograph/__init__.py
biocartograph/composition.py
biocartograph/enrichment.py
biocartograph/models.py
biocartograph/quantification.py
biocartograph/special.py
biocartograph/visualisation.py
biocartograph-0.10.20.dist-info/LICENSE
biocartograph-0.10.20.dist-info/METADATA
biocartograph-0.10.20.dist-info/WHEEL
biocartograph-0.10.20.dist-info/top_level.txt
biocartograph-0.10.20.dist-info/RECORD
