Metadata-Version: 2.1
Name: biocartograph
Version: 0.10.20
Summary: Package was renamed from Biocarta v0.2.27 to Biocartograph because of an unintentional name clash
Home-page: https://github.com/rictjo/biocarta
Author: Richard Tjörnhammar
Author-email: richard.tjornhammar@gmail.com
Classifier: Programming Language :: Python :: 3.9
Classifier: License :: OSI Approved :: Apache Software License
Classifier: Operating System :: OS Independent
License-File: LICENSE
